{"linked_list2.py": [{"type": "method", "rank": "B", "name": "remove", "col_offset": 4, "classname": "LinkedList", "complexity": 6, "lineno": 68, "endline": 78, "closures": []}, {"type": "method", "rank": "A", "name": "__init__", "col_offset": 4, "classname": "LinkedList", "complexity": 4, "lineno": 30, "endline": 39, "closures": []}, {"type": "class", "rank": "A", "name": "LinkedList", "col_offset": 0, "complexity": 3, "lineno": 16, "endline": 87, "methods": [{"type": "method", "rank": "A", "name": "__init__", "col_offset": 4, "classname": "LinkedList", "complexity": 4, "lineno": 30, "endline": 39, "closures": []}, {"type": "method", "rank": "A", "name": "push", "col_offset": 4, "classname": "LinkedList", "complexity": 1, "lineno": 41, "endline": 45, "closures": []}, {"type": "method", "rank": "A", "name": "pop", "col_offset": 4, "classname": "LinkedList", "complexity": 2, "lineno": 47, "endline": 54, "closures": []}, {"type": "method", "rank": "A", "name": "size", "col_offset": 4, "classname": "LinkedList", "complexity": 1, "lineno": 56, "endline": 58, "closures": []}, {"type": "method", "rank": "A", "name": "search", "col_offset": 4, "classname": "LinkedList", "complexity": 3, "lineno": 60, "endline": 66, "closures": []}, {"type": "method", "rank": "B", "name": "remove", "col_offset": 4, "classname": "LinkedList", "complexity": 6, "lineno": 68, "endline": 78, "closures": []}, {"type": "method", "rank": "A", "name": "display", "col_offset": 4, "classname": "LinkedList", "complexity": 2, "lineno": 80, "endline": 87, "closures": []}]}, {"type": "method", "rank": "A", "name": "search", "col_offset": 4, "classname": "LinkedList", "complexity": 3, "lineno": 60, "endline": 66, "closures": []}, {"type": "class", "rank": "A", "name": "Node", "col_offset": 0, "complexity": 2, "lineno": 4, "endline": 13, "methods": [{"type": "method", "rank": "A", "name": "__init__", "col_offset": 4, "classname": "Node", "complexity": 1, "lineno": 10, "endline": 13, "closures": []}]}, {"type": "method", "rank": "A", "name": "pop", "col_offset": 4, "classname": "LinkedList", "complexity": 2, "lineno": 47, "endline": 54, "closures": []}, {"type": "method", "rank": "A", "name": "display", "col_offset": 4, "classname": "LinkedList", "complexity": 2, "lineno": 80, "endline": 87, "closures": []}, {"type": "method", "rank": "A", "name": "__init__", "col_offset": 4, "classname": "Node", "complexity": 1, "lineno": 10, "endline": 13, "closures": []}, {"type": "method", "rank": "A", "name": "push", "col_offset": 4, "classname": "LinkedList", "complexity": 1, "lineno": 41, "endline": 45, "closures": []}, {"type": "method", "rank": "A", "name": "size", "col_offset": 4, "classname": "LinkedList", "complexity": 1, "lineno": 56, "endline": 58, "closures": []}]}
